<login>  <flowControlInfo>    <delayBeforeChallenge>-1</delayBeforeChallenge>    <delayBeforeLoginComplete>1</delayBeforeLoginComplete>    <delayAfterLoginComplete>1</delayAfterLoginComplete>    <expireToken>false</expireToken>  </flowControlInfo>  <SecurityQuestionAnswerList>    <SecurityQuestionAnswer>      <Question>What is the name of your state?</Question>      <Answer>Texas</Answer>    </SecurityQuestionAnswer>    <SecurityQuestionAnswer>      <Question>What is the name of your first school</Question>      <Answer>w3schools</Answer>    </SecurityQuestionAnswer>  </SecurityQuestionAnswerList>  <SelectedSecurityQuestionAnswerList>    <SelectedSecurityQuestionAnswer>      <Question>What is the name of your state?</Question>      <Answer>Texas</Answer>    </SelectedSecurityQuestionAnswer>    <SelectedSecurityQuestionAnswer>      <Question>What is the name of your first school</Question>      <Answer>w3schools</Answer>    </SelectedSecurityQuestionAnswer>    <SelectedSecurityQuestionAnswer>      <Question>What is the name of your best friend</Question>      <Answer>Drona</Answer>    </SelectedSecurityQuestionAnswer>  </SelectedSecurityQuestionAnswerList></login>
